napari_cosmos_ts-0.3.6.dist-info/METADATA
napari_cosmos_ts-0.3.6.dist-info/WHEEL
napari_cosmos_ts-0.3.6.dist-info/entry_points.txt
napari_cosmos_ts-0.3.6.dist-info/licenses/LICENSE
napari_cosmos_ts/__init__.py
napari_cosmos_ts/main_widget.py
napari_cosmos_ts/napari.yaml
napari_cosmos_ts-0.3.6.dist-info/RECORD
