Metadata-Version: 2.1
Name: napari-cosmos-ts
Version: 0.3.6
Summary: napari plugin for colocalization single-molecule spectroscopy (CoSMoS) time series (TS) analysis
Author: Marcel Goldschen-Ohm
Author-Email: Marcel Goldschen-Ohm <goldschen-ohm@utexas.edu>
Classifier: Development Status :: 4 - Beta
Classifier: Intended Audience :: Science/Research
Classifier: License :: OSI Approved :: MIT License
Classifier: Framework :: napari
Classifier: Programming Language :: Python :: 3 :: Only
Project-URL: homepage, https://github.com/marcel-goldschen-ohm/napari-cosmos-ts
Project-URL: repository, https://github.com/marcel-goldschen-ohm/napari-cosmos-ts
Requires-Python: >=3.10
Requires-Dist: numpy<2.1,>=2.0
Requires-Dist: qtpy>=2.4.1
Requires-Dist: pyqtgraph>=0.13.4
Requires-Dist: pystackreg>=0.2.7
Requires-Dist: pycpd>=2.0.0
Requires-Dist: qtawesome>=1.3.1
Requires-Dist: h5py>=3.11.0
